async8ball/__init__.py
async8ball/decorators.py
async8ball-2.0.9.dist-info/LICENSE
async8ball-2.0.9.dist-info/METADATA
async8ball-2.0.9.dist-info/WHEEL
async8ball-2.0.9.dist-info/top_level.txt
async8ball-2.0.9.dist-info/RECORD
