Metadata-Version: 2.1
Name: async8ball
Version: 2.0.9
Summary: Asynchronous 8ball response generator.
Home-page: https://github.com/Cryptex-github/async8ball
Author: cryptex
License: Apache-2.0
Keywords: async,8ball
Platform: UNKNOWN
Classifier: Development Status :: 3 - Alpha
Classifier: Intended Audience :: Developers
Classifier: License :: OSI Approved :: Apache Software License
Classifier: Natural Language :: English
Classifier: Programming Language :: Python :: 3 :: Only
Requires-Python: >=3.4
Requires-Dist: aiofile
